[{"url":"https://so.toutiao.com/search?keyword=陪伴观赛国足客场鏖战沙特","word":"陪伴观赛国足客场鏖战沙特"},{"url":"https://so.toutiao.com/search?keyword=华为新品发布会","word":"华为新品发布会"},{"url":"https://so.toutiao.com/search?keyword=中国外贸持续发力新兴市场","word":"中国外贸持续发力新兴市场"},{"url":"https://so.toutiao.com/search?keyword=千禾0酱油公司股价四天蒸发9.5亿","word":"千禾0酱油公司股价四天蒸发9.5亿"},{"url":"https://so.toutiao.com/search?keyword=为何胡塞发射导弹无法命中美航母","word":"为何胡塞发射导弹无法命中美航母"},{"url":"https://so.toutiao.com/search?keyword=中国对4名加拿大籍毒贩执行死刑","word":"中国对4名加拿大籍毒贩执行死刑"},{"url":"https://so.toutiao.com/search?keyword=谁给尼日尔的底气驱逐中石油高管","word":"谁给尼日尔的底气驱逐中石油高管"},{"url":"https://so.toutiao.com/search?keyword=华为阔折叠Pura%20X售价7499元起","word":"华为阔折叠Pura X售价7499元起"},{"url":"https://so.toutiao.com/search?keyword=专家谈酱油里为什么会有砷和镉","word":"专家谈酱油里为什么会有砷和镉"},{"url":"https://so.toutiao.com/search?keyword=天津一税务局将开展税务抽查？假的","word":"天津一税务局将开展税务抽查？假的"},{"url":"https://so.toutiao.com/search?keyword=业内：香港再无“四大家族”","word":"业内：香港再无“四大家族”"},{"url":"https://so.toutiao.com/search?keyword=特朗普：我们会和中俄友好相处","word":"特朗普：我们会和中俄友好相处"},{"url":"https://so.toutiao.com/search?keyword=许家印被曝还有两名未成年子女","word":"许家印被曝还有两名未成年子女"},{"url":"https://so.toutiao.com/search?keyword=大V：巴拿马港口交易有两大结局","word":"大V：巴拿马港口交易有两大结局"},{"url":"https://so.toutiao.com/search?keyword=台退将：台军对解放军已无预警时间","word":"台退将：台军对解放军已无预警时间"},{"url":"https://so.toutiao.com/search?keyword=华为Pura%20X真机上手体验","word":"华为Pura X真机上手体验"},{"url":"https://so.toutiao.com/search?keyword=霍启刚：我是坚决爱国的","word":"霍启刚：我是坚决爱国的"},{"url":"https://so.toutiao.com/search?keyword=谢浩男爸爸抖音粉丝突破百万","word":"谢浩男爸爸抖音粉丝突破百万"},{"url":"https://so.toutiao.com/search?keyword=男子出差坐高铁偶遇列车长妻子","word":"男子出差坐高铁偶遇列车长妻子"},{"url":"https://so.toutiao.com/search?keyword=余承东用6个“敢于”介绍Pura%20X","word":"余承东用6个“敢于”介绍Pura X"},{"url":"https://so.toutiao.com/search?keyword=土耳其金融市场崩盘对中国有何影响","word":"土耳其金融市场崩盘对中国有何影响"},{"url":"https://so.toutiao.com/search?keyword=伊万：沙特联赛外援挤占本土球员空间","word":"伊万：沙特联赛外援挤占本土球员空间"},{"url":"https://so.toutiao.com/search?keyword=男子发现他人忘拔银行卡狂取1万元","word":"男子发现他人忘拔银行卡狂取1万元"},{"url":"https://so.toutiao.com/search?keyword=金秀贤因脱裤洗碗照起诉金赛纶家属","word":"金秀贤因脱裤洗碗照起诉金赛纶家属"},{"url":"https://so.toutiao.com/search?keyword=余承东一喊刘亦菲全场欢呼","word":"余承东一喊刘亦菲全场欢呼"},{"url":"https://so.toutiao.com/search?keyword=女子上厕所时车子被小孩弄倒","word":"女子上厕所时车子被小孩弄倒"},{"url":"https://so.toutiao.com/search?keyword=“千禾0”不意味零添加？品牌回应","word":"“千禾0”不意味零添加？品牌回应"},{"url":"https://so.toutiao.com/search?keyword=刘亦菲将和余承东一起直播","word":"刘亦菲将和余承东一起直播"},{"url":"https://so.toutiao.com/search?keyword=高管女儿能开盒多少人的隐私","word":"高管女儿能开盒多少人的隐私"},{"url":"https://so.toutiao.com/search?keyword=女生手卡在男生嘴里拔不出求助医院","word":"女生手卡在男生嘴里拔不出求助医院"},{"url":"https://so.toutiao.com/search?keyword=2025款问界M9上市%2046.98万起售","word":"2025款问界M9上市 46.98万起售"},{"url":"https://so.toutiao.com/search?keyword=日本晋级世界杯%20森保一眼含热泪","word":"日本晋级世界杯 森保一眼含热泪"},{"url":"https://so.toutiao.com/search?keyword=赵露思大量取关%20全网仅剩14个关注","word":"赵露思大量取关 全网仅剩14个关注"},{"url":"https://so.toutiao.com/search?keyword=华为Pura%20X全面搭载鸿蒙5","word":"华为Pura X全面搭载鸿蒙5"},{"url":"https://so.toutiao.com/search?keyword=*ST仁东：重整计划执行完毕","word":"*ST仁东：重整计划执行完毕"},{"url":"https://so.toutiao.com/search?keyword=4名加籍毒贩被执行死刑%20外交部回应","word":"4名加籍毒贩被执行死刑 外交部回应"},{"url":"https://so.toutiao.com/search?keyword=刘亦菲担任智界品牌大使","word":"刘亦菲担任智界品牌大使"},{"url":"https://so.toutiao.com/search?keyword=问界M5%20Ultra上市%20售22.98万元起","word":"问界M5 Ultra上市 售22.98万元起"},{"url":"https://so.toutiao.com/search?keyword=走失23年的海外游子回国认亲","word":"走失23年的海外游子回国认亲"},{"url":"https://so.toutiao.com/search?keyword=国足客战沙特23人大名单公布","word":"国足客战沙特23人大名单公布"},{"url":"https://so.toutiao.com/search?keyword=河南一厂区爆炸3人失联4人受伤","word":"河南一厂区爆炸3人失联4人受伤"},{"url":"https://so.toutiao.com/search?keyword=贪3.43亿%20西藏原书记吴英杰受审","word":"贪3.43亿 西藏原书记吴英杰受审"},{"url":"https://so.toutiao.com/search?keyword=余承东：华为ADS%204今年三季度发布","word":"余承东：华为ADS 4今年三季度发布"},{"url":"https://so.toutiao.com/search?keyword=妹妹眼中的谢浩男","word":"妹妹眼中的谢浩男"},{"url":"https://so.toutiao.com/search?keyword=年近80的霍震霆每天坚持打网球","word":"年近80的霍震霆每天坚持打网球"},{"url":"https://so.toutiao.com/search?keyword=男子抛弃妻儿16年后起诉儿子要赡养费","word":"男子抛弃妻儿16年后起诉儿子要赡养费"},{"url":"https://so.toutiao.com/search?keyword=美乌总统再通话谈妥两大问题","word":"美乌总统再通话谈妥两大问题"},{"url":"https://so.toutiao.com/search?keyword=百度确认开盒信息并非从内部泄露","word":"百度确认开盒信息并非从内部泄露"},{"url":"https://so.toutiao.com/search?keyword=谢浩男父亲辟谣有6岁儿子","word":"谢浩男父亲辟谣有6岁儿子"},{"url":"https://so.toutiao.com/search?keyword=美议员欲禁中国人留学%20骆家辉警告","word":"美议员欲禁中国人留学 骆家辉警告"}]